{"description":{"title":"Mississippi June Precipitation","units":"Inches","base_period":"1901-2000","missing":"-99"},"data":{"189506":{"value":"6.09","anomaly":"2.00"},"189606":{"value":"5.20","anomaly":"1.11"},"189706":{"value":"1.92","anomaly":"-2.17"},"189806":{"value":"4.56","anomaly":"0.47"},"189906":{"value":"3.63","anomaly":"-0.46"},"190006":{"value":"12.05","anomaly":"7.96"},"190106":{"value":"2.33","anomaly":"-1.76"},"190206":{"value":"1.80","anomaly":"-2.29"},"190306":{"value":"3.19","anomaly":"-0.90"},"190406":{"value":"4.30","anomaly":"0.21"},"190506":{"value":"4.83","anomaly":"0.74"},"190606":{"value":"3.24","anomaly":"-0.85"},"190706":{"value":"2.39","anomaly":"-1.70"},"190806":{"value":"4.77","anomaly":"0.68"},"190906":{"value":"6.77","anomaly":"2.68"},"191006":{"value":"6.55","anomaly":"2.46"},"191106":{"value":"4.69","anomaly":"0.60"},"191206":{"value":"4.92","anomaly":"0.83"},"191306":{"value":"2.23","anomaly":"-1.86"},"191406":{"value":"2.25","anomaly":"-1.84"},"191506":{"value":"4.56","anomaly":"0.47"},"191606":{"value":"4.11","anomaly":"0.02"},"191706":{"value":"2.77","anomaly":"-1.32"},"191806":{"value":"3.99","anomaly":"-0.10"},"191906":{"value":"5.00","anomaly":"0.91"},"192006":{"value":"4.31","anomaly":"0.22"},"192106":{"value":"3.08","anomaly":"-1.01"},"192206":{"value":"3.92","anomaly":"-0.17"},"192306":{"value":"5.27","anomaly":"1.18"},"192406":{"value":"3.66","anomaly":"-0.43"},"192506":{"value":"2.48","anomaly":"-1.61"},"192606":{"value":"3.41","anomaly":"-0.68"},"192706":{"value":"5.22","anomaly":"1.13"},"192806":{"value":"9.65","anomaly":"5.56"},"192906":{"value":"3.31","anomaly":"-0.78"},"193006":{"value":"0.53","anomaly":"-3.56"},"193106":{"value":"2.39","anomaly":"-1.70"},"193206":{"value":"3.34","anomaly":"-0.75"},"193306":{"value":"1.86","anomaly":"-2.23"},"193406":{"value":"5.77","anomaly":"1.68"},"193506":{"value":"4.27","anomaly":"0.18"},"193606":{"value":"1.38","anomaly":"-2.71"},"193706":{"value":"4.40","anomaly":"0.31"},"193806":{"value":"5.15","anomaly":"1.06"},"193906":{"value":"6.83","anomaly":"2.74"},"194006":{"value":"6.13","anomaly":"2.04"},"194106":{"value":"3.60","anomaly":"-0.49"},"194206":{"value":"4.45","anomaly":"0.36"},"194306":{"value":"2.89","anomaly":"-1.20"},"194406":{"value":"1.78","anomaly":"-2.31"},"194506":{"value":"5.17","anomaly":"1.08"},"194606":{"value":"5.97","anomaly":"1.88"},"194706":{"value":"4.44","anomaly":"0.35"},"194806":{"value":"3.12","anomaly":"-0.97"},"194906":{"value":"5.86","anomaly":"1.77"},"195006":{"value":"4.09","anomaly":"0.00"},"195106":{"value":"4.89","anomaly":"0.80"},"195206":{"value":"1.13","anomaly":"-2.96"},"195306":{"value":"2.55","anomaly":"-1.54"},"195406":{"value":"1.78","anomaly":"-2.31"},"195506":{"value":"3.11","anomaly":"-0.98"},"195606":{"value":"4.47","anomaly":"0.38"},"195706":{"value":"7.60","anomaly":"3.51"},"195806":{"value":"5.83","anomaly":"1.74"},"195906":{"value":"4.62","anomaly":"0.53"},"196006":{"value":"2.41","anomaly":"-1.68"},"196106":{"value":"6.66","anomaly":"2.57"},"196206":{"value":"4.78","anomaly":"0.69"},"196306":{"value":"3.94","anomaly":"-0.15"},"196406":{"value":"3.17","anomaly":"-0.92"},"196506":{"value":"3.47","anomaly":"-0.62"},"196606":{"value":"1.81","anomaly":"-2.28"},"196706":{"value":"2.78","anomaly":"-1.31"},"196806":{"value":"2.45","anomaly":"-1.64"},"196906":{"value":"2.14","anomaly":"-1.95"},"197006":{"value":"4.48","anomaly":"0.39"},"197106":{"value":"3.90","anomaly":"-0.19"},"197206":{"value":"3.63","anomaly":"-0.46"},"197306":{"value":"3.13","anomaly":"-0.96"},"197406":{"value":"6.12","anomaly":"2.03"},"197506":{"value":"5.36","anomaly":"1.27"},"197606":{"value":"4.08","anomaly":"-0.01"},"197706":{"value":"2.21","anomaly":"-1.88"},"197806":{"value":"4.61","anomaly":"0.52"},"197906":{"value":"2.71","anomaly":"-1.38"},"198006":{"value":"3.64","anomaly":"-0.45"},"198106":{"value":"3.77","anomaly":"-0.32"},"198206":{"value":"4.69","anomaly":"0.60"},"198306":{"value":"6.31","anomaly":"2.22"},"198406":{"value":"2.67","anomaly":"-1.42"},"198506":{"value":"3.28","anomaly":"-0.81"},"198606":{"value":"4.25","anomaly":"0.16"},"198706":{"value":"5.18","anomaly":"1.09"},"198806":{"value":"1.23","anomaly":"-2.86"},"198906":{"value":"9.98","anomaly":"5.89"},"199006":{"value":"3.82","anomaly":"-0.27"},"199106":{"value":"4.10","anomaly":"0.01"},"199206":{"value":"6.75","anomaly":"2.66"},"199306":{"value":"4.40","anomaly":"0.31"},"199406":{"value":"6.22","anomaly":"2.13"},"199506":{"value":"2.92","anomaly":"-1.17"},"199606":{"value":"4.74","anomaly":"0.65"},"199706":{"value":"7.34","anomaly":"3.25"},"199806":{"value":"2.38","anomaly":"-1.71"},"199906":{"value":"5.05","anomaly":"0.96"},"200006":{"value":"4.51","anomaly":"0.42"},"200106":{"value":"6.58","anomaly":"2.49"},"200206":{"value":"3.23","anomaly":"-0.86"},"200306":{"value":"8.01","anomaly":"3.92"},"200406":{"value":"9.65","anomaly":"5.56"},"200506":{"value":"3.42","anomaly":"-0.67"},"200606":{"value":"1.78","anomaly":"-2.31"},"200706":{"value":"3.16","anomaly":"-0.93"},"200806":{"value":"2.50","anomaly":"-1.59"},"200906":{"value":"1.55","anomaly":"-2.54"},"201006":{"value":"3.11","anomaly":"-0.98"},"201106":{"value":"3.26","anomaly":"-0.83"},"201206":{"value":"3.46","anomaly":"-0.63"},"201306":{"value":"4.15","anomaly":"0.06"},"201406":{"value":"6.96","anomaly":"2.87"},"201506":{"value":"4.05","anomaly":"-0.04"},"201606":{"value":"3.71","anomaly":"-0.38"},"201706":{"value":"9.39","anomaly":"5.30"},"201806":{"value":"3.87","anomaly":"-0.22"},"201906":{"value":"5.24","anomaly":"1.15"},"202006":{"value":"6.35","anomaly":"2.26"},"202106":{"value":"9.59","anomaly":"5.50"},"202206":{"value":"2.65","anomaly":"-1.44"},"202306":{"value":"5.61","anomaly":"1.52"}}}